pret_pycrdt-0.12.44.post2.dist-info/METADATA
pret_pycrdt-0.12.44.post2.dist-info/WHEEL
pret_pycrdt-0.12.44.post2.dist-info/licenses/LICENSE
pycrdt/__init__.py
pycrdt/_array.py
pycrdt/_awareness.py
pycrdt/_base.py
pycrdt/_doc.py
pycrdt/_map.py
pycrdt/_provider.py
pycrdt/_pycrdt.cp312-win32.pyd
pycrdt/_pycrdt.pyi
pycrdt/_snapshot.py
pycrdt/_sticky_index.py
pycrdt/_sync.py
pycrdt/_text.py
pycrdt/_transaction.py
pycrdt/_undo.py
pycrdt/_update.py
pycrdt/_version.py
pycrdt/_xml.py
pycrdt/py.typed
pret_pycrdt-0.12.44.post2.dist-info/RECORD
